{
    "wsh @ laa": {
        "jo adell": {
            "fd": "+280"
        },
        "mike trout": {
            "fd": "+280"
        },
        "logan ohoppe": {
            "fd": "+370"
        },
        "taylor ward": {
            "fd": "+380"
        },
        "james wood": {
            "fd": "+380"
        },
        "": {
            "fd": "+500"
        },
        "nathaniel lowe": {
            "fd": "+550"
        },
        "luis rengifo": {
            "fd": "+600"
        },
        "josh bell": {
            "fd": "+650"
        },
        "nolan schanuel": {
            "fd": "+700"
        },
        "luis garcia": {
            "fd": "+750"
        },
        "lamonte wade": {
            "fd": "+750"
        },
        "brady house": {
            "fd": "+800"
        },
        "daylen lile": {
            "fd": "+850"
        },
        "riley adams": {
            "fd": "+850"
        },
        "christian moore": {
            "fd": "+950"
        },
        "kevin newman": {
            "fd": "+1200"
        },
        "jacob young": {
            "fd": "+1900"
        }
    },
    "mia @ ari": {
        "eugenio suarez": {
            "fd": "+255"
        },
        "ketel marte": {
            "fd": "+370"
        },
        "lourdes gurriel": {
            "fd": "+500"
        },
        "agustin ramirez": {
            "fd": "+560"
        },
        "jesus sanchez": {
            "fd": "+600"
        },
        "josh naylor": {
            "fd": "+630"
        },
        "pavin smith": {
            "fd": "+630"
        },
        "kyle stowers": {
            "fd": "+750"
        },
        "connor norby": {
            "fd": "+830"
        },
        "alek thomas": {
            "fd": "+900"
        },
        "eric wagaman": {
            "fd": "+900"
        },
        "otto lopez": {
            "fd": "+900"
        },
        "geraldo perdomo": {
            "fd": "+900"
        },
        "heriberto hernandez": {
            "fd": "+1000"
        },
        "jake mccarthy": {
            "fd": "+1060"
        },
        "javier sanoja": {
            "fd": "+1100"
        },
        "xavier edwards": {
            "fd": "+1400"
        },
        "jose herrera": {
            "fd": "+2000"
        }
    }
}