{
    "laa @ nyy": {
        "aaron judge": {
            "pn": "342/-539"
        },
        "mike trout": {
            "pn": "346/-547"
        },
        "taylor ward": {
            "pn": "577/-1182"
        },
        "logan ohoppe": {
            "pn": "570/-1160"
        },
        "zach neto": {
            "pn": "558/-1117"
        },
        "jo adell": {
            "pn": "576/-1179"
        },
        "giancarlo stanton": {
            "pn": "447/-784"
        }
    },
    "bos @ sea": {
        "jorge polanco": {
            "pn": "570/-1157"
        },
        "cal raleigh": {
            "pn": "269/-398"
        },
        "randy arozarena": {
            "pn": "535/-1040"
        },
        "julio rodriguez": {
            "pn": "384/-631"
        },
        "jarren duran": {
            "pn": "552/-1096"
        },
        "dominic canzone": {
            "pn": "577/-1184"
        }
    },
    "col @ wsh": {
        "ryan mcmahon": {
            "pn": "398/-664"
        },
        "cj abrams": {
            "pn": "554/-1103"
        },
        "jordan beck": {
            "pn": "555/-1106"
        },
        "james wood": {
            "pn": "407/-685"
        },
        "hunter goodman": {
            "pn": "349/-554"
        },
        "mickey moniak": {
            "pn": "585/-1213"
        },
        "michael toglia": {
            "pn": "505/-946"
        },
        "brady house": {
            "pn": "603/-1281"
        },
        "riley adams": {
            "pn": "555/-1106"
        },
        "andres chaparro": {
            "pn": "382/-626"
        }
    },
    "phi @ mia": {
        "max kepler": {
            "pn": "594/-1245"
        },
        "kyle schwarber": {
            "pn": "353/-562"
        },
        "jesus sanchez": {
            "pn": "462/-824"
        },
        "kyle stowers": {
            "pn": "481/-877"
        },
        "agustin ramirez": {
            "pn": "530/-1024"
        }
    },
    "hou @ ath": {
        "christian walker": {
            "pn": "343/-540"
        },
        "brent rooker": {
            "pn": "244/-352"
        },
        "lawrence butler": {
            "pn": "396/-659"
        },
        "yainer diaz": {
            "pn": "471/-849"
        },
        "tyler soderstrom": {
            "pn": "395/-656"
        },
        "luis urias": {
            "pn": "581/-1197"
        },
        "nick kurtz": {
            "pn": "576/-1179"
        }
    },
    "sd @ lad": {
        "freddie freeman": {
            "pn": "453/-801"
        },
        "max muncy": {
            "pn": "448/-788"
        },
        "manny machado": {
            "pn": "358/-574"
        },
        "mookie betts": {
            "pn": "508/-956"
        },
        "teoscar hernandez": {
            "pn": "464/-829"
        },
        "michael conforto": {
            "pn": "544/-1070"
        },
        "shohei ohtani": {
            "pn": "212/-298"
        },
        "fernando tatis": {
            "pn": "341/-538"
        },
        "will smith": {
            "pn": "547/-1079"
        },
        "andy pages": {
            "pn": "468/-842"
        }
    },
    "bal @ tb": {
        "cedric mullins": {
            "pn": "574/-1172"
        },
        "ryan ohearn": {
            "pn": "588/-1223"
        },
        "ramon laureano": {
            "pn": "537/-1047"
        },
        "brandon lowe": {
            "pn": "447/-786"
        },
        "jonathan aranda": {
            "pn": "453/-800"
        },
        "josh lowe": {
            "pn": "546/-1076"
        },
        "adley rutschman": {
            "pn": "576/-1181"
        },
        "jordan westburg": {
            "pn": "458/-815"
        },
        "colton cowser": {
            "pn": "513/-972"
        },
        "gunnar henderson": {
            "pn": "340/-536"
        },
        "junior caminero": {
            "pn": "390/-644"
        }
    }
}